topsis_mnvu05/__init__.py
topsis_mnvu05/topsismnvu.py
topsis_mnvu05-0.0.5.dist-info/LICENSE.txt
topsis_mnvu05-0.0.5.dist-info/METADATA
topsis_mnvu05-0.0.5.dist-info/WHEEL
topsis_mnvu05-0.0.5.dist-info/top_level.txt
topsis_mnvu05-0.0.5.dist-info/RECORD
