Metadata-Version: 2.1
Name: topsis-mnvu05
Version: 0.0.5
Summary: TOPSIS Package
Home-page: https://github.com/mnvu/topsis
Author: Manav Upadhyay
Author-email: manavupadhyay5@gmail.com
License: UNKNOWN
Platform: UNKNOWN
Classifier: Programming Language :: Python :: 3
Classifier: License :: OSI Approved :: MIT License
Classifier: Operating System :: OS Independent
Requires-Python: >=3.6
